{
    "format_version": 6,
    "joint_skeleton": "locomotion:block_entity/shulker_box",
    "length": 2.958,
    "time_markers": {},
    "custom_attributes": {},
    "joint_channels": {
        "base_jnt": {
            "translation": {
                "0.0": [
                    0.0,
                    24.0,
                    -0.0
                ]
            },
            "rotation": {
                "0.0": [
                    0.0,
                    0.0,
                    -0.0
                ]
            },
            "scale": {
                "0.0": [
                    1.0,
                    1.0,
                    1.0
                ]
            },
            "visibility": {
                "0.0": true
            }
        },
        "lid_jnt": {
            "translation": {
                "0.0": [
                    0.0,
                    24.0,
                    -0.0
                ],
                "0.208": [
                    0.0,
                    24.0,
                    -0.0
                ],
                "0.25": [
                    0.0,
                    23.859,
                    -0.0
                ],
                "0.292": [
                    0.0,
                    23.477,
                    -0.0
                ],
                "0.333": [
                    0.0,
                    22.914,
                    -0.0
                ],
                "0.375": [
                    0.0,
                    22.229,
                    -0.0
                ],
                "0.417": [
                    0.0,
                    21.483,
                    -0.0
                ],
                "0.458": [
                    0.0,
                    20.736,
                    -0.0
                ],
                "0.5": [
                    0.0,
                    20.048,
                    -0.0
                ],
                "0.542": [
                    0.0,
                    19.479,
                    -0.0
                ],
                "0.583": [
                    0.0,
                    18.964,
                    -0.0
                ],
                "0.625": [
                    0.0,
                    18.408,
                    -0.0
                ],
                "0.667": [
                    0.0,
                    17.829,
                    -0.0
                ],
                "0.708": [
                    0.0,
                    17.242,
                    -0.0
                ],
                "0.75": [
                    0.0,
                    16.664,
                    -0.0
                ],
                "0.792": [
                    0.0,
                    16.11,
                    -0.0
                ],
                "0.833": [
                    0.0,
                    15.597,
                    -0.0
                ],
                "0.875": [
                    0.0,
                    15.141,
                    -0.0
                ],
                "0.917": [
                    0.0,
                    14.758,
                    -0.0
                ],
                "0.958": [
                    0.0,
                    14.464,
                    -0.0
                ],
                "1.0": [
                    0.0,
                    14.276,
                    -0.0
                ],
                "1.042": [
                    0.0,
                    14.21,
                    -0.0
                ],
                "1.458": [
                    0.0,
                    14.21,
                    -0.0
                ],
                "1.5": [
                    0.0,
                    14.28,
                    -0.0
                ],
                "1.542": [
                    0.0,
                    14.48,
                    -0.0
                ],
                "1.583": [
                    0.0,
                    14.791,
                    -0.0
                ],
                "1.625": [
                    0.0,
                    15.196,
                    -0.0
                ],
                "1.667": [
                    0.0,
                    15.679,
                    -0.0
                ],
                "1.708": [
                    0.0,
                    16.222,
                    -0.0
                ],
                "1.75": [
                    0.0,
                    16.808,
                    -0.0
                ],
                "1.792": [
                    0.0,
                    17.419,
                    -0.0
                ],
                "1.833": [
                    0.0,
                    18.039,
                    -0.0
                ],
                "1.875": [
                    0.0,
                    18.65,
                    -0.0
                ],
                "1.917": [
                    0.0,
                    19.234,
                    -0.0
                ],
                "1.958": [
                    0.0,
                    19.776,
                    -0.0
                ],
                "2.0": [
                    0.0,
                    20.257,
                    -0.0
                ],
                "2.042": [
                    0.0,
                    20.737,
                    -0.0
                ],
                "2.083": [
                    0.0,
                    21.268,
                    -0.0
                ],
                "2.125": [
                    0.0,
                    21.821,
                    -0.0
                ],
                "2.167": [
                    0.0,
                    22.367,
                    -0.0
                ],
                "2.208": [
                    0.0,
                    22.879,
                    -0.0
                ],
                "2.25": [
                    0.0,
                    23.326,
                    -0.0
                ],
                "2.292": [
                    0.0,
                    23.681,
                    -0.0
                ],
                "2.333": [
                    0.0,
                    23.916,
                    -0.0
                ],
                "2.375": [
                    0.0,
                    24.0,
                    -0.0
                ]
            },
            "rotation": {
                "0.0": [
                    0.0,
                    0.0,
                    -0.0
                ],
                "0.542": [
                    0.0,
                    0.0,
                    -0.0
                ],
                "0.583": [
                    0.0,
                    -3.542,
                    -0.0
                ],
                "0.625": [
                    0.0,
                    -13.333,
                    -0.0
                ],
                "0.667": [
                    0.0,
                    -28.125,
                    -0.0
                ],
                "0.708": [
                    0.0,
                    -46.667,
                    -0.0
                ],
                "0.75": [
                    0.0,
                    -67.708,
                    -0.0
                ],
                "0.792": [
                    -0.0,
                    -90.0,
                    -0.0
                ],
                "0.833": [
                    0.0,
                    -112.292,
                    -0.0
                ],
                "0.875": [
                    0.0,
                    -133.333,
                    -0.0
                ],
                "0.917": [
                    0.0,
                    -151.875,
                    -0.0
                ],
                "0.958": [
                    0.0,
                    -166.667,
                    -0.0
                ],
                "1.0": [
                    0.0,
                    -176.458,
                    -0.0
                ],
                "1.042": [
                    0.0,
                    -180.0,
                    -0.0
                ],
                "1.458": [
                    0.0,
                    -180.0,
                    -0.0
                ],
                "1.5": [
                    0.0,
                    -183.031,
                    -0.0
                ],
                "1.542": [
                    0.0,
                    -191.47,
                    -0.0
                ],
                "1.583": [
                    0.0,
                    -204.333,
                    -0.0
                ],
                "1.625": [
                    0.0,
                    -220.637,
                    -0.0
                ],
                "1.667": [
                    0.0,
                    -239.399,
                    -0.0
                ],
                "1.708": [
                    0.0,
                    -259.636,
                    -0.0
                ],
                "1.75": [
                    0.0,
                    79.636,
                    -0.0
                ],
                "1.792": [
                    0.0,
                    59.399,
                    -0.0
                ],
                "1.833": [
                    0.0,
                    40.637,
                    -0.0
                ],
                "1.875": [
                    0.0,
                    24.333,
                    -0.0
                ],
                "1.917": [
                    0.0,
                    11.47,
                    -0.0
                ],
                "1.958": [
                    0.0,
                    3.031,
                    -0.0
                ],
                "2.0": [
                    0.0,
                    0.0,
                    -0.0
                ]
            },
            "scale": {
                "0.0": [
                    1.0,
                    1.0,
                    1.0
                ]
            },
            "visibility": {
                "0.0": true
            }
        },
        "root_jnt": {
            "translation": {
                "0.0": [
                    0.0,
                    -0.0,
                    -0.0
                ]
            },
            "rotation": {
                "0.0": [
                    0.0,
                    -0.0,
                    -0.0
                ]
            },
            "scale": {
                "0.0": [
                    1.0,
                    1.0,
                    1.0
                ]
            },
            "visibility": {
                "0.0": true
            }
        }
    }
}