{
    "format_version": 5,
    "joint_skeleton": "locomotion:entity/player/first_person",
    "length": 0.883,
    "time_markers": {},
    "custom_attributes": {
        "crossbow_pull_property": {
            "0.0": 0.0
        },
        "use_duration_property": {
            "0.0": 0.0
        },
        "is_using_property": {
            "0.0": 0.0
        }
    },
    "joint_channels": {
        "arm_L_buffer_jnt": {
            "translation": {
                "0.0": [
                    12.667,
                    12.349,
                    -10.657
                ]
            },
            "rotation": {
                "0.0": [
                    0.0,
                    0.0,
                    -0.0
                ]
            },
            "scale": {
                "0.0": [
                    1.0,
                    1.0,
                    1.0
                ]
            },
            "visibility": {
                "0.0": true
            }
        },
        "arm_L_jnt": {
            "translation": {
                "0.0": [
                    0.0,
                    0.0,
                    0.0
                ]
            },
            "rotation": {
                "0.0": [
                    1.095,
                    28.324,
                    5.571
                ]
            },
            "scale": {
                "0.0": [
                    1.0,
                    1.0,
                    1.0
                ]
            },
            "visibility": {
                "0.0": true
            }
        },
        "arm_R_buffer_jnt": {
            "translation": {
                "0.0": [
                    -12.666,
                    12.349,
                    -10.657
                ]
            },
            "rotation": {
                "0.0": [
                    0.0,
                    0.0,
                    -0.0
                ]
            },
            "scale": {
                "0.0": [
                    1.0,
                    1.0,
                    1.0
                ]
            },
            "visibility": {
                "0.0": true
            }
        },
        "arm_R_jnt": {
            "translation": {
                "0.0": [
                    0.444,
                    10.621,
                    -4.053
                ],
                "0.017": [
                    0.515,
                    9.6,
                    -4.053
                ],
                "0.033": [
                    0.934,
                    7.574,
                    -4.053
                ],
                "0.05": [
                    2.007,
                    6.101,
                    -4.053
                ],
                "0.067": [
                    4.04,
                    5.34,
                    -4.053
                ],
                "0.083": [
                    6.273,
                    4.478,
                    -4.056
                ],
                "0.1": [
                    6.958,
                    3.617,
                    -4.056
                ],
                "0.117": [
                    6.116,
                    2.861,
                    -4.045
                ],
                "0.133": [
                    4.869,
                    2.311,
                    -4.011
                ],
                "0.15": [
                    3.697,
                    2.069,
                    -3.944
                ],
                "0.167": [
                    2.808,
                    2.033,
                    -3.833
                ],
                "0.183": [
                    2.085,
                    2.027,
                    -3.658
                ],
                "0.2": [
                    1.515,
                    2.043,
                    -3.416
                ],
                "0.217": [
                    1.086,
                    2.076,
                    -3.13
                ],
                "0.233": [
                    0.785,
                    2.119,
                    -2.818
                ],
                "0.25": [
                    0.601,
                    2.165,
                    -2.502
                ],
                "0.267": [
                    0.52,
                    2.208,
                    -2.202
                ],
                "0.283": [
                    0.492,
                    2.242,
                    -1.938
                ],
                "0.3": [
                    0.469,
                    2.259,
                    -1.732
                ],
                "0.317": [
                    0.453,
                    2.264,
                    -1.602
                ],
                "0.333": [
                    0.441,
                    2.263,
                    -1.529
                ],
                "0.35": [
                    0.434,
                    2.258,
                    -1.477
                ],
                "0.367": [
                    0.43,
                    2.25,
                    -1.443
                ],
                "0.383": [
                    0.429,
                    2.24,
                    -1.423
                ],
                "0.4": [
                    0.431,
                    2.229,
                    -1.413
                ],
                "0.417": [
                    0.433,
                    2.218,
                    -1.411
                ],
                "0.433": [
                    0.437,
                    2.208,
                    -1.412
                ],
                "0.45": [
                    0.44,
                    2.2,
                    -1.413
                ],
                "0.467": [
                    0.443,
                    2.195,
                    -1.413
                ],
                "0.483": [
                    0.444,
                    2.193,
                    -1.413
                ],
                "0.5": [
                    0.444,
                    2.193,
                    -1.413
                ],
                "0.517": [
                    0.444,
                    2.195,
                    -1.413
                ],
                "0.533": [
                    0.444,
                    2.199,
                    -1.413
                ],
                "0.55": [
                    0.444,
                    2.203,
                    -1.413
                ],
                "0.567": [
                    0.444,
                    2.209,
                    -1.413
                ],
                "0.583": [
                    0.444,
                    2.214,
                    -1.413
                ],
                "0.6": [
                    0.444,
                    2.219,
                    -1.413
                ],
                "0.617": [
                    0.444,
                    2.224,
                    -1.413
                ],
                "0.633": [
                    0.444,
                    2.227,
                    -1.413
                ],
                "0.65": [
                    0.444,
                    2.23,
                    -1.413
                ],
                "0.667": [
                    0.444,
                    2.23,
                    -1.413
                ],
                "0.683": [
                    0.444,
                    2.229,
                    -1.413
                ],
                "0.7": [
                    0.444,
                    2.227,
                    -1.413
                ],
                "0.717": [
                    0.444,
                    2.226,
                    -1.413
                ],
                "0.733": [
                    0.444,
                    2.224,
                    -1.413
                ],
                "0.75": [
                    0.444,
                    2.223,
                    -1.413
                ],
                "0.767": [
                    0.444,
                    2.221,
                    -1.413
                ],
                "0.783": [
                    0.444,
                    2.219,
                    -1.413
                ],
                "0.8": [
                    0.444,
                    2.218,
                    -1.413
                ],
                "0.817": [
                    0.444,
                    2.216,
                    -1.413
                ],
                "0.833": [
                    0.444,
                    2.214,
                    -1.413
                ],
                "0.85": [
                    0.444,
                    2.213,
                    -1.413
                ],
                "0.867": [
                    0.444,
                    2.212,
                    -1.413
                ],
                "0.883": [
                    0.444,
                    2.211,
                    -1.413
                ]
            },
            "rotation": {
                "0.0": [
                    2.106,
                    -37.89,
                    10.821
                ],
                "0.017": [
                    -0.922,
                    -37.031,
                    12.843
                ],
                "0.033": [
                    -10.216,
                    -33.882,
                    18.233
                ],
                "0.05": [
                    -25.246,
                    -27.03,
                    25.447
                ],
                "0.067": [
                    -41.442,
                    -17.079,
                    30.407
                ],
                "0.083": [
                    -55.805,
                    -6.866,
                    31.426
                ],
                "0.1": [
                    -69.27,
                    2.184,
                    29.33
                ],
                "0.117": [
                    -82.167,
                    9.084,
                    24.996
                ],
                "0.133": [
                    -94.105,
                    13.361,
                    19.46
                ],
                "0.15": [
                    -104.166,
                    15.124,
                    13.844
                ],
                "0.167": [
                    -111.328,
                    14.951,
                    9.03
                ],
                "0.183": [
                    -114.78,
                    13.62,
                    5.422
                ],
                "0.2": [
                    -115.905,
                    11.947,
                    2.6
                ],
                "0.217": [
                    -116.54,
                    10.316,
                    0.116
                ],
                "0.233": [
                    -116.764,
                    8.827,
                    -2.012
                ],
                "0.25": [
                    -116.659,
                    7.559,
                    -3.754
                ],
                "0.267": [
                    -116.325,
                    6.506,
                    -5.199
                ],
                "0.283": [
                    -115.857,
                    5.625,
                    -6.476
                ],
                "0.3": [
                    -115.33,
                    4.921,
                    -7.596
                ],
                "0.317": [
                    -114.819,
                    4.389,
                    -8.567
                ],
                "0.333": [
                    -114.393,
                    4.024,
                    -9.391
                ],
                "0.35": [
                    -114.115,
                    3.772,
                    -10.053
                ],
                "0.367": [
                    -113.953,
                    3.589,
                    -10.53
                ],
                "0.383": [
                    -113.839,
                    3.485,
                    -10.815
                ],
                "0.4": [
                    -113.767,
                    3.457,
                    -10.908
                ],
                "0.417": [
                    -113.734,
                    3.476,
                    -10.876
                ],
                "0.433": [
                    -113.737,
                    3.509,
                    -10.797
                ],
                "0.45": [
                    -113.77,
                    3.553,
                    -10.681
                ],
                "0.467": [
                    -113.827,
                    3.604,
                    -10.542
                ],
                "0.483": [
                    -113.902,
                    3.657,
                    -10.392
                ],
                "0.5": [
                    -113.988,
                    3.709,
                    -10.242
                ],
                "0.517": [
                    -114.08,
                    3.754,
                    -10.106
                ],
                "0.533": [
                    -114.17,
                    3.789,
                    -9.995
                ],
                "0.55": [
                    -114.254,
                    3.81,
                    -9.921
                ],
                "0.567": [
                    -114.324,
                    3.81,
                    -9.896
                ],
                "0.583": [
                    -114.373,
                    3.8,
                    -9.904
                ],
                "0.6": [
                    -114.391,
                    3.79,
                    -9.92
                ],
                "0.617": [
                    -114.393,
                    3.78,
                    -9.941
                ],
                "0.633": [
                    -114.395,
                    3.768,
                    -9.969
                ],
                "0.65": [
                    -114.397,
                    3.753,
                    -10.002
                ],
                "0.667": [
                    -114.399,
                    3.736,
                    -10.038
                ],
                "0.683": [
                    -114.402,
                    3.719,
                    -10.077
                ],
                "0.7": [
                    -114.404,
                    3.701,
                    -10.116
                ],
                "0.717": [
                    -114.407,
                    3.684,
                    -10.154
                ],
                "0.733": [
                    -114.409,
                    3.668,
                    -10.19
                ],
                "0.75": [
                    -114.411,
                    3.653,
                    -10.223
                ],
                "0.767": [
                    -114.413,
                    3.64,
                    -10.251
                ],
                "0.783": [
                    -114.414,
                    3.63,
                    -10.273
                ],
                "0.8": [
                    -114.415,
                    3.624,
                    -10.287
                ],
                "0.817": [
                    -114.416,
                    3.622,
                    -10.292
                ]
            },
            "scale": {
                "0.0": [
                    1.0,
                    1.0,
                    1.0
                ]
            },
            "visibility": {
                "0.0": true
            }
        },
        "arm_buffer_jnt": {
            "translation": {
                "0.0": [
                    -0.0,
                    0.0,
                    0.0
                ]
            },
            "rotation": {
                "0.0": [
                    0.0,
                    0.0,
                    -0.0
                ]
            },
            "scale": {
                "0.0": [
                    1.0,
                    1.0,
                    1.0
                ]
            },
            "visibility": {
                "0.0": true
            }
        },
        "camera_jnt": {
            "translation": {
                "0.0": [
                    0.0,
                    0.0,
                    -0.0
                ]
            },
            "rotation": {
                "0.0": [
                    0.0,
                    0.0,
                    -0.0
                ]
            },
            "scale": {
                "0.0": [
                    1.0,
                    1.0,
                    1.0
                ]
            },
            "visibility": {
                "0.0": true
            }
        },
        "hand_L_jnt": {
            "translation": {
                "0.0": [
                    1.0,
                    9.0,
                    0.0
                ]
            },
            "rotation": {
                "0.0": [
                    0.0,
                    -0.0,
                    0.0
                ]
            },
            "scale": {
                "0.0": [
                    1.0,
                    1.0,
                    1.0
                ]
            },
            "visibility": {
                "0.0": true
            }
        },
        "hand_R_jnt": {
            "translation": {
                "0.0": [
                    -1.0,
                    9.0,
                    0.0
                ],
                "0.05": [
                    -1.0,
                    9.0,
                    0.0
                ],
                "0.067": [
                    -1.0,
                    9.276,
                    0.076
                ],
                "0.083": [
                    -1.0,
                    9.883,
                    0.243
                ],
                "0.1": [
                    -1.0,
                    10.49,
                    0.41
                ],
                "0.117": [
                    -1.0,
                    10.766,
                    0.486
                ],
                "0.133": [
                    -1.0,
                    10.725,
                    0.467
                ],
                "0.15": [
                    -1.0,
                    10.612,
                    0.416
                ],
                "0.167": [
                    -1.0,
                    10.443,
                    0.342
                ],
                "0.183": [
                    -1.0,
                    10.235,
                    0.251
                ],
                "0.2": [
                    -1.0,
                    10.003,
                    0.152
                ],
                "0.217": [
                    -1.0,
                    9.763,
                    0.054
                ],
                "0.233": [
                    -1.0,
                    9.531,
                    -0.037
                ],
                "0.25": [
                    -1.0,
                    9.322,
                    -0.112
                ],
                "0.267": [
                    -1.0,
                    9.154,
                    -0.163
                ],
                "0.283": [
                    -1.0,
                    9.041,
                    -0.181
                ],
                "0.3": [
                    -1.0,
                    9.0,
                    -0.14
                ],
                "0.317": [
                    -1.0,
                    9.0,
                    -0.048
                ],
                "0.333": [
                    -1.0,
                    9.0,
                    0.042
                ],
                "0.35": [
                    -1.0,
                    9.0,
                    0.082
                ],
                "0.367": [
                    -1.0,
                    9.0,
                    0.076
                ],
                "0.383": [
                    -1.0,
                    9.0,
                    0.065
                ],
                "0.4": [
                    -1.0,
                    9.0,
                    0.05
                ],
                "0.417": [
                    -1.0,
                    9.0,
                    0.032
                ],
                "0.433": [
                    -1.0,
                    9.0,
                    0.013
                ],
                "0.45": [
                    -1.0,
                    9.0,
                    -0.006
                ],
                "0.467": [
                    -1.0,
                    9.0,
                    -0.022
                ],
                "0.483": [
                    -1.0,
                    9.0,
                    -0.036
                ],
                "0.5": [
                    -1.0,
                    9.0,
                    -0.044
                ],
                "0.517": [
                    -1.0,
                    9.0,
                    -0.049
                ],
                "0.533": [
                    -1.0,
                    9.0,
                    -0.052
                ],
                "0.55": [
                    -1.0,
                    9.0,
                    -0.052
                ],
                "0.567": [
                    -1.0,
                    9.0,
                    -0.051
                ],
                "0.583": [
                    -1.0,
                    9.0,
                    -0.049
                ],
                "0.6": [
                    -1.0,
                    9.0,
                    -0.046
                ],
                "0.617": [
                    -1.0,
                    9.0,
                    -0.042
                ],
                "0.633": [
                    -1.0,
                    9.0,
                    -0.037
                ],
                "0.65": [
                    -1.0,
                    9.0,
                    -0.032
                ],
                "0.667": [
                    -1.0,
                    9.0,
                    -0.026
                ],
                "0.683": [
                    -1.0,
                    9.0,
                    -0.02
                ],
                "0.7": [
                    -1.0,
                    9.0,
                    -0.015
                ],
                "0.717": [
                    -1.0,
                    9.0,
                    -0.01
                ],
                "0.733": [
                    -1.0,
                    9.0,
                    -0.006
                ],
                "0.75": [
                    -1.0,
                    9.0,
                    -0.003
                ],
                "0.767": [
                    -1.0,
                    9.0,
                    -0.001
                ],
                "0.783": [
                    -1.0,
                    9.0,
                    0.0
                ]
            },
            "rotation": {
                "0.0": [
                    -0.0,
                    0.0,
                    -5.225
                ],
                "0.017": [
                    37.327,
                    9.238,
                    -11.888
                ],
                "0.033": [
                    75.707,
                    19.96,
                    -4.97
                ],
                "0.05": [
                    74.617,
                    20.356,
                    -5.467
                ],
                "0.067": [
                    71.076,
                    20.065,
                    -8.271
                ],
                "0.083": [
                    65.446,
                    18.411,
                    -13.377
                ],
                "0.1": [
                    58.969,
                    15.589,
                    -18.395
                ],
                "0.117": [
                    52.509,
                    12.652,
                    -21.319
                ],
                "0.133": [
                    46.079,
                    9.984,
                    -22.446
                ],
                "0.15": [
                    39.563,
                    6.988,
                    -23.0
                ],
                "0.167": [
                    33.149,
                    3.953,
                    -22.96
                ],
                "0.183": [
                    27.032,
                    1.121,
                    -22.35
                ],
                "0.2": [
                    21.425,
                    -1.298,
                    -21.259
                ],
                "0.217": [
                    16.576,
                    -3.146,
                    -19.826
                ],
                "0.233": [
                    12.516,
                    -4.419,
                    -18.19
                ],
                "0.25": [
                    9.064,
                    -5.212,
                    -16.449
                ],
                "0.267": [
                    6.185,
                    -5.579,
                    -14.68
                ],
                "0.283": [
                    3.844,
                    -5.58,
                    -12.938
                ],
                "0.3": [
                    2.002,
                    -5.276,
                    -11.265
                ],
                "0.317": [
                    0.614,
                    -4.723,
                    -9.685
                ],
                "0.333": [
                    -0.37,
                    -3.989,
                    -8.218
                ],
                "0.35": [
                    -1.003,
                    -3.16,
                    -6.874
                ],
                "0.367": [
                    -1.341,
                    -2.309,
                    -5.661
                ],
                "0.383": [
                    -1.442,
                    -1.502,
                    -4.591
                ],
                "0.4": [
                    -1.395,
                    -0.797,
                    -3.677
                ],
                "0.417": [
                    -1.264,
                    -0.244,
                    -2.939
                ],
                "0.433": [
                    -1.07,
                    0.115,
                    -2.401
                ],
                "0.45": [
                    -0.834,
                    0.24,
                    -1.993
                ],
                "0.467": [
                    -0.578,
                    0.23,
                    -1.629
                ],
                "0.483": [
                    -0.322,
                    0.208,
                    -1.308
                ],
                "0.5": [
                    -0.087,
                    0.175,
                    -1.028
                ],
                "0.517": [
                    0.106,
                    0.135,
                    -0.788
                ],
                "0.533": [
                    0.236,
                    0.091,
                    -0.584
                ],
                "0.55": [
                    0.282,
                    0.046,
                    -0.416
                ],
                "0.567": [
                    0.275,
                    0.003,
                    -0.28
                ],
                "0.583": [
                    0.263,
                    -0.034,
                    -0.173
                ],
                "0.6": [
                    0.246,
                    -0.064,
                    -0.094
                ],
                "0.617": [
                    0.225,
                    -0.083,
                    -0.041
                ],
                "0.633": [
                    0.202,
                    -0.091,
                    -0.01
                ],
                "0.65": [
                    0.176,
                    -0.089,
                    -0.0
                ],
                "0.667": [
                    0.149,
                    -0.086,
                    -0.0
                ],
                "0.683": [
                    0.121,
                    -0.081,
                    -0.0
                ],
                "0.7": [
                    0.095,
                    -0.075,
                    -0.0
                ],
                "0.717": [
                    0.069,
                    -0.067,
                    -0.0
                ],
                "0.733": [
                    0.047,
                    -0.059,
                    -0.0
                ],
                "0.75": [
                    0.028,
                    -0.05,
                    -0.0
                ],
                "0.767": [
                    0.013,
                    -0.041,
                    -0.0
                ],
                "0.783": [
                    0.003,
                    -0.032,
                    -0.0
                ],
                "0.8": [
                    0.0,
                    -0.023,
                    -0.0
                ],
                "0.817": [
                    0.0,
                    -0.016,
                    -0.0
                ],
                "0.833": [
                    0.0,
                    -0.009,
                    -0.0
                ],
                "0.85": [
                    0.0,
                    -0.004,
                    -0.0
                ],
                "0.867": [
                    0.0,
                    -0.001,
                    -0.0
                ],
                "0.883": [
                    0.0,
                    0.0,
                    -0.0
                ]
            },
            "scale": {
                "0.0": [
                    1.0,
                    1.0,
                    1.0
                ]
            },
            "visibility": {
                "0.0": true
            }
        },
        "item_L_jnt": {
            "translation": {
                "0.0": [
                    0.0,
                    1.0,
                    -2.0
                ]
            },
            "rotation": {
                "0.0": [
                    -90.0,
                    -0.0,
                    -180.0
                ]
            },
            "scale": {
                "0.0": [
                    1.0,
                    1.0,
                    1.0
                ]
            },
            "visibility": {
                "0.0": true
            }
        },
        "item_R_jnt": {
            "translation": {
                "0.0": [
                    0.0,
                    1.0,
                    -2.0
                ]
            },
            "rotation": {
                "0.0": [
                    -90.0,
                    -0.0,
                    -180.0
                ]
            },
            "scale": {
                "0.0": [
                    1.0,
                    1.0,
                    1.0
                ]
            },
            "visibility": {
                "0.0": true
            }
        },
        "root_jnt": {
            "translation": {
                "0.0": [
                    0.0,
                    -0.0,
                    -0.0
                ]
            },
            "rotation": {
                "0.0": [
                    0.0,
                    -0.0,
                    -0.0
                ]
            },
            "scale": {
                "0.0": [
                    1.0,
                    1.0,
                    1.0
                ]
            },
            "visibility": {
                "0.0": true
            }
        }
    }
}